[
    {
        "code": "58d4320af375a7c7ba9223cf92ad4723",
        "env": "d6a7fefa3210f9f90460ac77cae72131",
        "classPathWhitelistHash": "835491922"
    },
    [
        {
            "fromName": "res_2",
            "toName": "res_2",
            "prefix": [
                
            ],
            "importType": {
                "$type": "ammonite.util.ImportData.ImportType",
                "name": "Term"
            }
        },
        {
            "fromName": "output",
            "toName": "output",
            "prefix": [
                
            ],
            "importType": {
                "$type": "ammonite.util.ImportData.ImportType",
                "name": "Term"
            }
        },
        {
            "fromName": "$routes",
            "toName": "$routes",
            "prefix": [
                
            ],
            "importType": {
                "$type": "ammonite.util.ImportData.ImportType",
                "name": "Term"
            }
        },
        {
            "fromName": "flexibleFizzBuzz",
            "toName": "flexibleFizzBuzz",
            "prefix": [
                
            ],
            "importType": {
                "$type": "ammonite.util.ImportData.ImportType",
                "name": "Term"
            }
        },
        {
            "fromName": "$routesOuter",
            "toName": "$routesOuter",
            "prefix": [
                
            ],
            "importType": {
                "$type": "ammonite.util.ImportData.ImportType",
                "name": "Term"
            }
        },
        {
            "fromName": "res_5",
            "toName": "res_5",
            "prefix": [
                
            ],
            "importType": {
                "$type": "ammonite.util.ImportData.ImportType",
                "name": "Term"
            }
        },
        {
            "fromName": "i_=",
            "toName": "i_=",
            "prefix": [
                
            ],
            "importType": {
                "$type": "ammonite.util.ImportData.ImportType",
                "name": "Term"
            }
        },
        {
            "fromName": "res_1",
            "toName": "res_1",
            "prefix": [
                
            ],
            "importType": {
                "$type": "ammonite.util.ImportData.ImportType",
                "name": "Term"
            }
        },
        {
            "fromName": "i",
            "toName": "i",
            "prefix": [
                
            ],
            "importType": {
                "$type": "ammonite.util.ImportData.ImportType",
                "name": "Term"
            }
        }
    ]
]